{
  "@class": "Animation",
  "id": {
    "uuid": "12F0D3D5-329C-4237-8552-394151BBA264"
  },
  "tracks": [
    {
      "@class": "Vector3BehaviorTrack",
      "clips": [
        {
          "@class": "Vector3BehaviorClip",
          "beginTime": 0,
          "duration": 1000,
          "script": "Vector3ValueBehaviorClipScript",
          "behavior": {
            "@class": "Vector3PlainBehavior",
            "times": [
              0,
              33,
              66,
              100,
              133,
              166,
              200,
              233,
              266,
              300,
              333,
              366,
              400,
              433,
              466,
              500,
              533,
              566,
              600,
              633,
              666,
              699,
              733,
              766,
              800,
              833,
              866,
              899,
              933,
              966,
              1000
            ],
            "values": [
              0,
              0.47814300656318665,
              0,
              0,
              0.47814300656318665,
              0,
              0,
              0.47814300656318665,
              0,
              0,
              0.47814300656318665,
              0,
              0,
              0.47814300656318665,
              0,
              0,
              0.47814300656318665,
              0,
              0,
              0.47814300656318665,
              0,
              0,
              0.47814300656318665,
              0,
              0,
              0.47814300656318665,
              0,
              0,
              0.47814300656318665,
              0,
              0,
              0.47814300656318665,
              0,
              0,
              0.47814300656318665,
              0,
              0,
              0.47814300656318665,
              0,
              0,
              0.47814300656318665,
              0,
              0,
              0.47814300656318665,
              0,
              0,
              0.47814300656318665,
              0,
              0,
              0.47814300656318665,
              0,
              0,
              0.47814300656318665,
              0,
              0,
              0.47814300656318665,
              0,
              0,
              0.47814300656318665,
              0,
              0,
              0.47814300656318665,
              0,
              0,
              0.47814300656318665,
              0,
              0,
              0.47814300656318665,
              0,
              0,
              0.47814300656318665,
              0,
              0,
              0.47814300656318665,
              0,
              0,
              0.47814300656318665,
              0,
              0,
              0.47814300656318665,
              0,
              0,
              0.47814300656318665,
              0,
              0,
              0.47814300656318665,
              0,
              0,
              0.47814300656318665,
              0,
              0,
              0.47814300656318665,
              0
            ]
          }
        }
      ],
      "script": "Vector3BehaviorTrackScript",
      "accessor": "PositionBlendAccessor"
    },
    {
      "@class": "QuaternionBehaviorTrack",
      "clips": [
        {
          "@class": "QuaternionBehaviorClip",
          "beginTime": 0,
          "duration": 1000,
          "script": "QuaternionValueBehaviorClipScript",
          "behavior": {
            "@class": "QuaternionPlainBehavior",
            "times": [
              0,
              33,
              66,
              100,
              133,
              166,
              200,
              233,
              266,
              300,
              333,
              366,
              400,
              433,
              466,
              500,
              533,
              566,
              600,
              633,
              666,
              699,
              733,
              766,
              800,
              833,
              866,
              899,
              933,
              966,
              1000
            ],
            "values": [
              0.9076111316680908,
              -0.05569100379943848,
              0.1037772074341774,
              -0.4029526710510254,
              -0.7752344012260437,
              0.1075771152973175,
              -0.0887141153216362,
              0.6160914301872253,
              -0.7039487361907959,
              0.11671652644872665,
              -0.04905882850289345,
              0.698875367641449,
              -0.7442162036895752,
              0.09222409874200821,
              -0.0385153666138649,
              0.6604192852973938,
              -0.7267595529556274,
              0.046535689383745193,
              -0.029599498957395554,
              0.6846742630004883,
              -0.578892707824707,
              -0.015381877310574055,
              -0.020479407161474228,
              0.8150014281272888,
              -0.5055438280105591,
              -0.03437426686286926,
              0.09456584602594376,
              0.8569137454032898,
              -0.5531326532363892,
              -0.026952147483825684,
              0.08256831765174866,
              0.8285531401634216,
              -0.5129250884056091,
              -0.013664000667631626,
              0.00698884529992938,
              0.8582961559295654,
              -0.596267819404602,
              0.009114883840084076,
              -0.019061502069234848,
              0.8025075197219849,
              -0.7085177898406982,
              0.08563358336687088,
              -0.038963086903095245,
              0.699393630027771,
              -0.7771903872489929,
              0.11254879832267761,
              -0.01241213921457529,
              0.6189942359924316,
              -0.8484078645706177,
              0.1013742983341217,
              0.005799566395580769,
              0.5195132493972778,
              0.9079874157905579,
              -0.07743194699287415,
              -0.03133001923561096,
              -0.41058677434921265,
              0.917892575263977,
              -0.08567426353693008,
              -0.02155536226928234,
              -0.3868700861930847,
              0.8802559971809387,
              -0.10712648928165436,
              0.005326041020452976,
              -0.46221742033958435,
              -0.7888892889022827,
              0.12120041251182556,
              -0.010898330248892307,
              0.6023664474487305,
              -0.6614356637001038,
              0.09964877367019653,
              0.004870566073805094,
              0.74333655834198,
              -0.5187621712684631,
              0.015723025426268578,
              0.05066738277673721,
              0.8532710075378418,
              -0.5097638368606567,
              -0.032491132616996765,
              0.07872699946165085,
              0.8560883402824402,
              -0.6237927079200745,
              -0.016989190131425858,
              0.09375547617673874,
              0.7757602334022522,
              -0.6390619277954102,
              0.06553797423839569,
              0.04605518653988838,
              0.7649729251861572,
              -0.6550810933113098,
              0.05835294350981712,
              0.048742666840553284,
              0.7517232298851013,
              -0.6894641518592834,
              -0.02293144166469574,
              0.07081238180398941,
              0.7204852104187012,
              -0.710768461227417,
              0.04876770079135895,
              -0.03312787041068077,
              0.700951099395752,
              -0.7808560132980347,
              0.055431295186281204,
              -0.04043925181031227,
              0.6209315657615662,
              -0.8605935573577881,
              0.02454487979412079,
              -0.01284860074520111,
              0.5085383057594299,
              0.9075329303741455,
              -0.012379157356917858,
              -0.01943759247660637,
              -0.41934821009635925,
              0.9211148619651794,
              0.0043841078877449036,
              -0.067630335688591,
              -0.38334622979164124,
              0.8986215591430664,
              0.001482830848544836,
              -0.06990183889865875,
              -0.433117538690567,
              0.880748450756073,
              -0.002135961316525936,
              -0.05037651211023331,
              -0.47089266777038574
            ]
          }
        }
      ],
      "script": "QuaternionBehaviorTrackScript",
      "accessor": "RotationQBlendAccessor"
    },
    {
      "@class": "Vector3BehaviorTrack",
      "clips": [
        {
          "@class": "Vector3BehaviorClip",
          "beginTime": 0,
          "duration": 1000,
          "script": "Vector3ValueBehaviorClipScript",
          "behavior": {
            "@class": "Vector3PlainBehavior",
            "times": [
              0,
              33,
              66,
              100,
              133,
              166,
              200,
              233,
              266,
              300,
              333,
              366,
              400,
              433,
              466,
              500,
              533,
              566,
              600,
              633,
              666,
              699,
              733,
              766,
              800,
              833,
              866,
              899,
              933,
              966,
              1000
            ],
            "values": [
              0.9999994039535522,
              1.0000007152557373,
              0.9999988079071045,
              1,
              1.000000238418579,
              0.9999987483024597,
              1,
              1.000000238418579,
              0.9999991059303284,
              0.999999463558197,
              1.0000004768371582,
              0.9999986290931702,
              0.9999994039535522,
              0.9999999403953552,
              0.9999986886978149,
              0.9999999403953552,
              1.0000003576278687,
              0.9999992251396179,
              0.9999995827674866,
              1,
              0.9999991059303284,
              0.9999998807907104,
              1.0000007152557373,
              0.9999989867210388,
              1.0000001192092896,
              1.0000005960464478,
              0.9999986886978149,
              0.9999998211860657,
              1.0000007152557373,
              0.9999986290931702,
              0.9999992847442627,
              1.0000003576278687,
              0.9999985098838806,
              0.999999463558197,
              1.000000238418579,
              0.9999991655349731,
              0.9999997615814209,
              1.0000008344650269,
              0.9999987483024597,
              0.9999995827674866,
              1.0000007152557373,
              0.9999985694885254,
              0.999999463558197,
              1.0000001192092896,
              0.9999988079071045,
              0.9999998807907104,
              1.0000004768371582,
              0.9999988079071045,
              0.9999995827674866,
              1.000000238418579,
              0.999998927116394,
              0.9999992251396179,
              1.0000001192092896,
              0.9999986886978149,
              0.9999998211860657,
              0.9999997615814209,
              0.9999992847442627,
              0.9999991655349731,
              1.0000004768371582,
              0.9999991059303284,
              0.999999463558197,
              1.0000001192092896,
              0.9999985694885254,
              0.9999996423721313,
              1.0000007152557373,
              0.9999991059303284,
              0.9999998211860657,
              1.000000238418579,
              0.9999990463256836,
              0.999999463558197,
              0.9999998807907104,
              0.9999992251396179,
              0.999999463558197,
              1,
              0.9999992847442627,
              0.9999999403953552,
              1.0000005960464478,
              0.9999988675117493,
              1,
              1.0000007152557373,
              0.9999990463256836,
              1.0000001192092896,
              1.0000007152557373,
              0.9999989867210388,
              0.9999991059303284,
              1.000000238418579,
              0.9999989867210388,
              0.9999999403953552,
              1.0000001192092896,
              0.9999985098838806,
              0.9999997019767761,
              1.0000001192092896,
              0.9999986886978149
            ]
          }
        }
      ],
      "script": "Vector3BehaviorTrackScript",
      "accessor": "ScaleBlendAccessor"
    }
  ]
}
