{
  "@class": "TimeLineScript",
  "id": {
    "uuid": "40A7DA28-6689-45B2-B68D-14CA9F743CCC"
  },
  "name": "anim_slide",
  "enableOnAwake": false,
  "loop": false,
  "jumpToFirstFrameAtEnd": false,
  "speed": 1,
  "weight": 1,
  "loopStartTime": 0,
  "loopDuration": 0,
  "is_imported": true,
  "type": "user",
  "scripts": {
    "@class": "StdListRuntimeScript",
    "list": [
      {
        "@class": "AnimationScript",
        "id": {
          "uuid": "1C492858-6CB5-4904-9409-1037EB6522F9"
        },
        "name": "AnimationScript",
        "enableOnAwake": false,
        "OwnerLink": {
          "@class": "BindingLink",
          "targetId": {
            "uuid": "041D8CFE-190A-4AAE-9440-B05179786DC0"
          }
        },
        "animation": {
          "uuid": "F89B3A9F-3983-4687-993F-F5D90EB010D1"
        },
        "AnimationType": "object3D",
        "is_imported": true,
        "isEnabled": true
      },
      {
        "@class": "AnimationScript",
        "id": {
          "uuid": "DEEFCF17-9B49-4852-BBD1-E7DF5D8F8A55"
        },
        "name": "AnimationScript",
        "enableOnAwake": false,
        "OwnerLink": {
          "@class": "BindingLink",
          "targetId": {
            "uuid": "0B4E8D4D-C3B5-4715-816B-C92415A2D09B"
          }
        },
        "animation": {
          "uuid": "11B6A05C-D517-496F-8A2F-57BD165CEE4F"
        },
        "AnimationType": "object3D",
        "is_imported": true,
        "isEnabled": true
      },
      {
        "@class": "AnimationScript",
        "id": {
          "uuid": "C883F98B-EBD9-4E8C-96D2-391CA88E7ED8"
        },
        "name": "AnimationScript",
        "enableOnAwake": false,
        "OwnerLink": {
          "@class": "BindingLink",
          "targetId": {
            "uuid": "0E0E50DB-4A9D-44AD-9939-D03F6C7CD798"
          }
        },
        "animation": {
          "uuid": "8A953EDA-63AE-4140-B130-D4F3A2C62EFE"
        },
        "AnimationType": "object3D",
        "is_imported": true,
        "isEnabled": true
      },
      {
        "@class": "AnimationScript",
        "id": {
          "uuid": "50DE1EB6-DADC-44AE-91FD-926623DBDDFB"
        },
        "name": "AnimationScript",
        "enableOnAwake": false,
        "OwnerLink": {
          "@class": "BindingLink",
          "targetId": {
            "uuid": "0E2F0A34-5AA8-41FE-ABED-F16E9C484046"
          }
        },
        "animation": {
          "uuid": "8F56447A-DAC8-45AC-8460-0234C20BAA34"
        },
        "AnimationType": "object3D",
        "is_imported": true,
        "isEnabled": true
      },
      {
        "@class": "AnimationScript",
        "id": {
          "uuid": "C02C7088-20C0-4150-A935-372A61C21E2A"
        },
        "name": "AnimationScript",
        "enableOnAwake": false,
        "OwnerLink": {
          "@class": "BindingLink",
          "targetId": {
            "uuid": "1481FC02-8720-4565-848B-00B5395BEBEC"
          }
        },
        "animation": {
          "uuid": "B56A32DC-A849-452F-B2E7-557209E9C814"
        },
        "AnimationType": "object3D",
        "is_imported": true,
        "isEnabled": true
      },
      {
        "@class": "AnimationScript",
        "id": {
          "uuid": "D928E2CE-46DF-4847-9D89-532900FFA0A2"
        },
        "name": "AnimationScript",
        "enableOnAwake": false,
        "OwnerLink": {
          "@class": "BindingLink",
          "targetId": {
            "uuid": "14E45E85-0179-4277-82B8-CE60ECF0BFD1"
          }
        },
        "animation": {
          "uuid": "B6D36205-163E-4BE1-B642-D2ADDE301AC5"
        },
        "AnimationType": "object3D",
        "is_imported": true,
        "isEnabled": true
      },
      {
        "@class": "AnimationScript",
        "id": {
          "uuid": "BB6F49D4-1A61-4000-89F4-38904726D769"
        },
        "name": "AnimationScript",
        "enableOnAwake": false,
        "OwnerLink": {
          "@class": "BindingLink",
          "targetId": {
            "uuid": "15E66C0D-4CF6-4264-964F-855809D90C96"
          }
        },
        "animation": {
          "uuid": "02361C68-1284-41FB-9FBC-70A68170109D"
        },
        "AnimationType": "object3D",
        "is_imported": true,
        "isEnabled": true
      },
      {
        "@class": "AnimationScript",
        "id": {
          "uuid": "51A05AE7-2423-423E-949B-C5735DE03370"
        },
        "name": "AnimationScript",
        "enableOnAwake": false,
        "OwnerLink": {
          "@class": "BindingLink",
          "targetId": {
            "uuid": "1AA1E958-228F-41D3-80A4-E9698DCF46DE"
          }
        },
        "animation": {
          "uuid": "E9ED0D48-63BB-40F5-97BD-4959CD9B33FF"
        },
        "AnimationType": "object3D",
        "is_imported": true,
        "isEnabled": true
      },
      {
        "@class": "AnimationScript",
        "id": {
          "uuid": "ADB69768-EDFF-4A2A-989D-011F3344567D"
        },
        "name": "AnimationScript",
        "enableOnAwake": false,
        "OwnerLink": {
          "@class": "BindingLink",
          "targetId": {
            "uuid": "1C17DD00-3647-4015-819A-4A00FCECB7DE"
          }
        },
        "animation": {
          "uuid": "46E483AE-EAA4-424E-BEF5-34004CE5C295"
        },
        "AnimationType": "object3D",
        "is_imported": true,
        "isEnabled": true
      },
      {
        "@class": "AnimationScript",
        "id": {
          "uuid": "AF3F2067-03F3-42BC-960C-3C7A259804A9"
        },
        "name": "AnimationScript",
        "enableOnAwake": false,
        "OwnerLink": {
          "@class": "BindingLink",
          "targetId": {
            "uuid": "23AFE6FD-6DCD-4741-9419-DC84BCE2A8BC"
          }
        },
        "animation": {
          "uuid": "350826CC-7DC8-42F4-8A1C-F1216DD3AD61"
        },
        "AnimationType": "object3D",
        "is_imported": true,
        "isEnabled": true
      },
      {
        "@class": "AnimationScript",
        "id": {
          "uuid": "C1D4D85F-0986-47B3-882D-73C459C96E2E"
        },
        "name": "AnimationScript",
        "enableOnAwake": false,
        "OwnerLink": {
          "@class": "BindingLink",
          "targetId": {
            "uuid": "27DC4AFE-D9E8-4164-B1B7-13C027584AD8"
          }
        },
        "animation": {
          "uuid": "8A44ACB5-5049-4925-85CC-F3BA8551BE01"
        },
        "AnimationType": "object3D",
        "is_imported": true,
        "isEnabled": true
      },
      {
        "@class": "AnimationScript",
        "id": {
          "uuid": "1D5259A8-E19F-4A64-B82F-5B7ABF36D536"
        },
        "name": "AnimationScript",
        "enableOnAwake": false,
        "OwnerLink": {
          "@class": "BindingLink",
          "targetId": {
            "uuid": "2A34C48D-C2AB-4FFC-84D0-A21FD132E9CC"
          }
        },
        "animation": {
          "uuid": "7FCBB582-C217-4D13-ADAB-04D4B72E9201"
        },
        "AnimationType": "object3D",
        "is_imported": true,
        "isEnabled": true
      },
      {
        "@class": "AnimationScript",
        "id": {
          "uuid": "59182DD6-3186-4CD5-B097-E853D47291F4"
        },
        "name": "AnimationScript",
        "enableOnAwake": false,
        "OwnerLink": {
          "@class": "BindingLink",
          "targetId": {
            "uuid": "2AC18390-25A8-457B-BA69-52222195A578"
          }
        },
        "animation": {
          "uuid": "0FBA96AE-E62C-4AD5-8B81-5A09FBB3B363"
        },
        "AnimationType": "object3D",
        "is_imported": true,
        "isEnabled": true
      },
      {
        "@class": "AnimationScript",
        "id": {
          "uuid": "BC59F950-97D0-4F0A-AD69-FF8EF1BFFD80"
        },
        "name": "AnimationScript",
        "enableOnAwake": false,
        "OwnerLink": {
          "@class": "BindingLink",
          "targetId": {
            "uuid": "2C7175D1-2154-4C0C-A07D-244D06ADF6C8"
          }
        },
        "animation": {
          "uuid": "E8A4D2B4-DE91-4C5C-A6C2-C8F8FC65770C"
        },
        "AnimationType": "object3D",
        "is_imported": true,
        "isEnabled": true
      },
      {
        "@class": "AnimationScript",
        "id": {
          "uuid": "EF09C448-610F-4306-A638-FEDEB4957289"
        },
        "name": "AnimationScript",
        "enableOnAwake": false,
        "OwnerLink": {
          "@class": "BindingLink",
          "targetId": {
            "uuid": "2E2F01CF-3F16-4360-A688-B7B799EF2A35"
          }
        },
        "animation": {
          "uuid": "8423A6C5-3FA1-4C8A-8EC4-3FA49314C1BA"
        },
        "AnimationType": "object3D",
        "is_imported": true,
        "isEnabled": true
      },
      {
        "@class": "AnimationScript",
        "id": {
          "uuid": "BDF09953-C069-4968-8A39-0B70B17BE718"
        },
        "name": "AnimationScript",
        "enableOnAwake": false,
        "OwnerLink": {
          "@class": "BindingLink",
          "targetId": {
            "uuid": "352BA52F-3211-43D9-B7AD-2B84F6DD4027"
          }
        },
        "animation": {
          "uuid": "5EAF2F2A-8B79-4754-A157-035761DCD2EE"
        },
        "AnimationType": "object3D",
        "is_imported": true,
        "isEnabled": true
      },
      {
        "@class": "AnimationScript",
        "id": {
          "uuid": "0831EC33-39A8-4E52-ADE4-50744DA3C318"
        },
        "name": "AnimationScript",
        "enableOnAwake": false,
        "OwnerLink": {
          "@class": "BindingLink",
          "targetId": {
            "uuid": "3A5E1643-562C-4CE1-B1F2-D0519B189CFB"
          }
        },
        "animation": {
          "uuid": "8F0ACCB7-1793-4083-9794-19E840CC14E5"
        },
        "AnimationType": "object3D",
        "is_imported": true,
        "isEnabled": true
      },
      {
        "@class": "AnimationScript",
        "id": {
          "uuid": "0D27B5DD-78FC-4DF8-A381-CF087AAB1FE6"
        },
        "name": "AnimationScript",
        "enableOnAwake": false,
        "OwnerLink": {
          "@class": "BindingLink",
          "targetId": {
            "uuid": "3DD39060-0680-47BC-9036-9B720AD1D611"
          }
        },
        "animation": {
          "uuid": "698DBF28-56F1-47EE-8BD4-2B37D1FD1E4F"
        },
        "AnimationType": "object3D",
        "is_imported": true,
        "isEnabled": true
      },
      {
        "@class": "AnimationScript",
        "id": {
          "uuid": "C64A6B0B-725D-4016-97C5-D417ECA70A58"
        },
        "name": "AnimationScript",
        "enableOnAwake": false,
        "OwnerLink": {
          "@class": "BindingLink",
          "targetId": {
            "uuid": "3DEFD571-9A3E-4F79-AF3D-F68FA3D3576F"
          }
        },
        "animation": {
          "uuid": "5A70113C-E114-49FD-96CD-42DE2192A6FB"
        },
        "AnimationType": "object3D",
        "is_imported": true,
        "isEnabled": true
      },
      {
        "@class": "AnimationScript",
        "id": {
          "uuid": "1B3EADAD-EA9B-48D3-B6C8-6909E49C07C8"
        },
        "name": "AnimationScript",
        "enableOnAwake": false,
        "OwnerLink": {
          "@class": "BindingLink",
          "targetId": {
            "uuid": "443C304A-F972-4020-A0A8-ACF224FE4FF3"
          }
        },
        "animation": {
          "uuid": "BCBC3E38-EE4A-4FAF-A81B-6692BF56F43B"
        },
        "AnimationType": "object3D",
        "is_imported": true,
        "isEnabled": true
      },
      {
        "@class": "AnimationScript",
        "id": {
          "uuid": "3F15D521-487A-4416-8CC7-E8D44E370886"
        },
        "name": "AnimationScript",
        "enableOnAwake": false,
        "OwnerLink": {
          "@class": "BindingLink",
          "targetId": {
            "uuid": "498FEA57-6A58-4490-8447-48B562D65A7A"
          }
        },
        "animation": {
          "uuid": "126EAFFF-1378-4E85-8D96-ACD637D54993"
        },
        "AnimationType": "object3D",
        "is_imported": true,
        "isEnabled": true
      },
      {
        "@class": "AnimationScript",
        "id": {
          "uuid": "8AF35832-36F1-41EC-B5FB-8110268E06C3"
        },
        "name": "AnimationScript",
        "enableOnAwake": false,
        "OwnerLink": {
          "@class": "BindingLink",
          "targetId": {
            "uuid": "4A4511FA-2C50-4118-B6A1-40AD3FDEE542"
          }
        },
        "animation": {
          "uuid": "D55E4ED2-1B44-41D0-8908-92C77D857C1A"
        },
        "AnimationType": "object3D",
        "is_imported": true,
        "isEnabled": true
      },
      {
        "@class": "AnimationScript",
        "id": {
          "uuid": "20993BC3-7FFC-48C1-B440-734C98250180"
        },
        "name": "AnimationScript",
        "enableOnAwake": false,
        "OwnerLink": {
          "@class": "BindingLink",
          "targetId": {
            "uuid": "4A733AE8-7C2E-4577-8496-8E88B36ADBE7"
          }
        },
        "animation": {
          "uuid": "1517F63A-16E4-4C90-AEF8-6413E089D515"
        },
        "AnimationType": "object3D",
        "is_imported": true,
        "isEnabled": true
      },
      {
        "@class": "AnimationScript",
        "id": {
          "uuid": "944DA5FA-40FD-4A93-B6D3-2A4798F5DE76"
        },
        "name": "AnimationScript",
        "enableOnAwake": false,
        "OwnerLink": {
          "@class": "BindingLink",
          "targetId": {
            "uuid": "4EC71978-2E95-41E3-ABD6-A7ED1F76CD48"
          }
        },
        "animation": {
          "uuid": "F3A27828-3275-46F0-BBF9-DC6375932557"
        },
        "AnimationType": "object3D",
        "is_imported": true,
        "isEnabled": true
      },
      {
        "@class": "AnimationScript",
        "id": {
          "uuid": "BA14D7D7-975D-40C6-A81D-5C16B2511643"
        },
        "name": "AnimationScript",
        "enableOnAwake": false,
        "OwnerLink": {
          "@class": "BindingLink",
          "targetId": {
            "uuid": "4FA54C1F-BE88-4E1B-87C8-5F259BCD9EAB"
          }
        },
        "animation": {
          "uuid": "A465F735-9D10-4C66-B446-6B4BFCC9879B"
        },
        "AnimationType": "object3D",
        "is_imported": true,
        "isEnabled": true
      },
      {
        "@class": "AnimationScript",
        "id": {
          "uuid": "8C0CCB9D-EA9B-4635-B9CE-B0E34B37499D"
        },
        "name": "AnimationScript",
        "enableOnAwake": false,
        "OwnerLink": {
          "@class": "BindingLink",
          "targetId": {
            "uuid": "52CE7257-80F3-4DEB-A646-0F1BEBA56B34"
          }
        },
        "animation": {
          "uuid": "267DDC5C-785C-4679-850A-3B11B98BD534"
        },
        "AnimationType": "object3D",
        "is_imported": true,
        "isEnabled": true
      },
      {
        "@class": "AnimationScript",
        "id": {
          "uuid": "7CB6337A-71C1-4647-B862-37B22A48F4EF"
        },
        "name": "AnimationScript",
        "enableOnAwake": false,
        "OwnerLink": {
          "@class": "BindingLink",
          "targetId": {
            "uuid": "57616EE8-9975-4AF6-B32C-1EC0AA401B2B"
          }
        },
        "animation": {
          "uuid": "B778859A-663D-4035-A716-518BB7606F61"
        },
        "AnimationType": "object3D",
        "is_imported": true,
        "isEnabled": true
      },
      {
        "@class": "AnimationScript",
        "id": {
          "uuid": "EE9A32CC-3FAC-41D4-AC33-2E3D84B3AA17"
        },
        "name": "AnimationScript",
        "enableOnAwake": false,
        "OwnerLink": {
          "@class": "BindingLink",
          "targetId": {
            "uuid": "577F07CA-775B-4BF4-AC82-DFF234587865"
          }
        },
        "animation": {
          "uuid": "F1BD8D93-5342-436B-ACFB-859FB9BB78E2"
        },
        "AnimationType": "object3D",
        "is_imported": true,
        "isEnabled": true
      },
      {
        "@class": "AnimationScript",
        "id": {
          "uuid": "DEFAD4A1-A919-47A3-8DD1-69D2D21A2BEA"
        },
        "name": "AnimationScript",
        "enableOnAwake": false,
        "OwnerLink": {
          "@class": "BindingLink",
          "targetId": {
            "uuid": "624867BE-392D-4719-A6E6-CE494376CC4E"
          }
        },
        "animation": {
          "uuid": "04A9B337-7588-4A54-8222-0605F1668B26"
        },
        "AnimationType": "object3D",
        "is_imported": true,
        "isEnabled": true
      },
      {
        "@class": "AnimationScript",
        "id": {
          "uuid": "C79D1A72-BFFC-4597-A06B-C9358C6AB52B"
        },
        "name": "AnimationScript",
        "enableOnAwake": false,
        "OwnerLink": {
          "@class": "BindingLink",
          "targetId": {
            "uuid": "628A7404-C9F9-491A-933C-0B60C65CC126"
          }
        },
        "animation": {
          "uuid": "0AC74A8B-94AA-4D4F-A42C-40A83CD51E98"
        },
        "AnimationType": "object3D",
        "is_imported": true,
        "isEnabled": true
      },
      {
        "@class": "AnimationScript",
        "id": {
          "uuid": "11B59D28-B07A-4D35-B835-27D8DD37996F"
        },
        "name": "AnimationScript",
        "enableOnAwake": false,
        "OwnerLink": {
          "@class": "BindingLink",
          "targetId": {
            "uuid": "6329A4BC-68B2-46CE-ABF2-909ED5D30020"
          }
        },
        "animation": {
          "uuid": "6F6A2F1D-ED4F-4EF6-B521-7E0ED114041B"
        },
        "AnimationType": "object3D",
        "is_imported": true,
        "isEnabled": true
      },
      {
        "@class": "AnimationScript",
        "id": {
          "uuid": "6D2E7F03-DBA9-4B48-8FA4-0B365A67B42B"
        },
        "name": "AnimationScript",
        "enableOnAwake": false,
        "OwnerLink": {
          "@class": "BindingLink",
          "targetId": {
            "uuid": "68FB23A2-3188-4D87-9AD1-1CE3D9886951"
          }
        },
        "animation": {
          "uuid": "188431E2-49C6-4EF2-9174-8BE03AEE5CA0"
        },
        "AnimationType": "object3D",
        "is_imported": true,
        "isEnabled": true
      },
      {
        "@class": "AnimationScript",
        "id": {
          "uuid": "24A188FF-A7D6-4139-9B66-2FA74BA4CA72"
        },
        "name": "AnimationScript",
        "enableOnAwake": false,
        "OwnerLink": {
          "@class": "BindingLink",
          "targetId": {
            "uuid": "690CEB95-0A2C-4FCA-A3F7-A40E9E1096F5"
          }
        },
        "animation": {
          "uuid": "D03931E8-93AE-48B9-931C-5EFB475782BC"
        },
        "AnimationType": "object3D",
        "is_imported": true,
        "isEnabled": true
      },
      {
        "@class": "AnimationScript",
        "id": {
          "uuid": "F78EE36D-CCC6-47B2-B5B9-6901ECBF99C1"
        },
        "name": "AnimationScript",
        "enableOnAwake": false,
        "OwnerLink": {
          "@class": "BindingLink",
          "targetId": {
            "uuid": "75E3D163-C830-4AB9-B499-56FA371AC254"
          }
        },
        "animation": {
          "uuid": "48C8B8D1-2830-4C30-B811-24AFFBA467A0"
        },
        "AnimationType": "object3D",
        "is_imported": true,
        "isEnabled": true
      },
      {
        "@class": "AnimationScript",
        "id": {
          "uuid": "FB691AD6-0A3B-4DDD-9C38-28023291B472"
        },
        "name": "AnimationScript",
        "enableOnAwake": false,
        "OwnerLink": {
          "@class": "BindingLink",
          "targetId": {
            "uuid": "799943C6-EA3E-4149-A2A1-1A530F58F5A2"
          }
        },
        "animation": {
          "uuid": "9D7F01B0-F9F3-49F2-8883-8DB8AE9314DD"
        },
        "AnimationType": "object3D",
        "is_imported": true,
        "isEnabled": true
      },
      {
        "@class": "AnimationScript",
        "id": {
          "uuid": "1425638F-49F5-4E24-993F-C3C5EE860FE8"
        },
        "name": "AnimationScript",
        "enableOnAwake": false,
        "OwnerLink": {
          "@class": "BindingLink",
          "targetId": {
            "uuid": "7C37F9A2-8CA4-4ACD-B3CC-4B363709658F"
          }
        },
        "animation": {
          "uuid": "5973D6EA-B409-431A-BD71-A6D2DE0F063D"
        },
        "AnimationType": "object3D",
        "is_imported": true,
        "isEnabled": true
      },
      {
        "@class": "AnimationScript",
        "id": {
          "uuid": "9CE70D32-D0F6-4178-99E9-FFE2417E5810"
        },
        "name": "AnimationScript",
        "enableOnAwake": false,
        "OwnerLink": {
          "@class": "BindingLink",
          "targetId": {
            "uuid": "7D6EF9E0-FF87-4149-9AC7-8346DE6D25DF"
          }
        },
        "animation": {
          "uuid": "16BD6DBD-99E5-41B0-9CBB-3AC9026804B0"
        },
        "AnimationType": "object3D",
        "is_imported": true,
        "isEnabled": true
      },
      {
        "@class": "AnimationScript",
        "id": {
          "uuid": "387C3BBD-BACE-4FA0-BD57-6227E1A62C4A"
        },
        "name": "AnimationScript",
        "enableOnAwake": false,
        "OwnerLink": {
          "@class": "BindingLink",
          "targetId": {
            "uuid": "83325F19-089B-474C-987C-E27DF43A0D1E"
          }
        },
        "animation": {
          "uuid": "28BDDDE0-5BB3-4A3D-85BE-774F97D55544"
        },
        "AnimationType": "object3D",
        "is_imported": true,
        "isEnabled": true
      },
      {
        "@class": "AnimationScript",
        "id": {
          "uuid": "DEE21E2A-C04F-4D04-A0EC-AE76C23712F9"
        },
        "name": "AnimationScript",
        "enableOnAwake": false,
        "OwnerLink": {
          "@class": "BindingLink",
          "targetId": {
            "uuid": "8ABF8607-5EF7-4AD4-8F51-0E2C52D26372"
          }
        },
        "animation": {
          "uuid": "7114F9E0-D69A-45C9-918B-9A2E0D31608A"
        },
        "AnimationType": "object3D",
        "is_imported": true,
        "isEnabled": true
      },
      {
        "@class": "AnimationScript",
        "id": {
          "uuid": "D796E745-B644-4742-A700-861DFECAB6A1"
        },
        "name": "AnimationScript",
        "enableOnAwake": false,
        "OwnerLink": {
          "@class": "BindingLink",
          "targetId": {
            "uuid": "9138733B-C772-49EC-9F62-824FAAF37CB7"
          }
        },
        "animation": {
          "uuid": "9486E61F-BE28-4F1D-AB43-028F5CE0782E"
        },
        "AnimationType": "object3D",
        "is_imported": true,
        "isEnabled": true
      },
      {
        "@class": "AnimationScript",
        "id": {
          "uuid": "4B273A52-5D72-4ED7-B046-B58F7EC1B508"
        },
        "name": "AnimationScript",
        "enableOnAwake": false,
        "OwnerLink": {
          "@class": "BindingLink",
          "targetId": {
            "uuid": "92DF9DA2-5914-44E6-8B7E-FAEA05EF9F92"
          }
        },
        "animation": {
          "uuid": "6C420B92-D4B2-4173-A426-327A6E001269"
        },
        "AnimationType": "object3D",
        "is_imported": true,
        "isEnabled": true
      },
      {
        "@class": "AnimationScript",
        "id": {
          "uuid": "A8CE43D8-F279-4E4E-928C-C0A6C19070FC"
        },
        "name": "AnimationScript",
        "enableOnAwake": false,
        "OwnerLink": {
          "@class": "BindingLink",
          "targetId": {
            "uuid": "979472E8-E1D9-4B66-A28A-EA015B2E29E9"
          }
        },
        "animation": {
          "uuid": "EE72A903-C2EA-4194-895F-747AAF6E1371"
        },
        "AnimationType": "object3D",
        "is_imported": true,
        "isEnabled": true
      },
      {
        "@class": "AnimationScript",
        "id": {
          "uuid": "9FC9BCA5-E6DA-4FF6-A7DC-DB2A94F145A3"
        },
        "name": "AnimationScript",
        "enableOnAwake": false,
        "OwnerLink": {
          "@class": "BindingLink",
          "targetId": {
            "uuid": "9EF5792F-72CE-4C35-8CFC-802C6437D9F3"
          }
        },
        "animation": {
          "uuid": "EB0A3722-515E-4DD1-96EE-ECD52E7E26C8"
        },
        "AnimationType": "object3D",
        "is_imported": true,
        "isEnabled": true
      },
      {
        "@class": "AnimationScript",
        "id": {
          "uuid": "C7894DCC-AB06-4E99-82F5-113D1E39B9F8"
        },
        "name": "AnimationScript",
        "enableOnAwake": false,
        "OwnerLink": {
          "@class": "BindingLink",
          "targetId": {
            "uuid": "9F0C15E7-0580-4C78-B337-CBB18DC92D07"
          }
        },
        "animation": {
          "uuid": "82CFC8DD-F081-4BBF-B8D8-616860FB1988"
        },
        "AnimationType": "object3D",
        "is_imported": true,
        "isEnabled": true
      },
      {
        "@class": "AnimationScript",
        "id": {
          "uuid": "0C48AE89-1B96-4D96-ABD0-D7F69BF44A4F"
        },
        "name": "AnimationScript",
        "enableOnAwake": false,
        "OwnerLink": {
          "@class": "BindingLink",
          "targetId": {
            "uuid": "A231659D-36E0-419A-BFF9-DD7809F58F88"
          }
        },
        "animation": {
          "uuid": "8B7ACD99-CE01-4E44-B7F9-07D0160A7E06"
        },
        "AnimationType": "object3D",
        "is_imported": true,
        "isEnabled": true
      },
      {
        "@class": "AnimationScript",
        "id": {
          "uuid": "4A4964C0-249B-4FFE-B425-3A1E44E9534F"
        },
        "name": "AnimationScript",
        "enableOnAwake": false,
        "OwnerLink": {
          "@class": "BindingLink",
          "targetId": {
            "uuid": "B5C70318-7039-4DEE-9BB4-C45972D6F5DE"
          }
        },
        "animation": {
          "uuid": "820AEA1F-A301-446A-B70B-44A3C660C5E9"
        },
        "AnimationType": "object3D",
        "is_imported": true,
        "isEnabled": true
      },
      {
        "@class": "AnimationScript",
        "id": {
          "uuid": "C1F1E53A-451A-49D2-AC51-8F55CB4EC50D"
        },
        "name": "AnimationScript",
        "enableOnAwake": false,
        "OwnerLink": {
          "@class": "BindingLink",
          "targetId": {
            "uuid": "BE2BE917-309B-4B52-A974-73380D749C0B"
          }
        },
        "animation": {
          "uuid": "164046C5-5148-4CCD-9661-1172CDC4D4E7"
        },
        "AnimationType": "object3D",
        "is_imported": true,
        "isEnabled": true
      },
      {
        "@class": "AnimationScript",
        "id": {
          "uuid": "E2832E81-9551-4F17-A1A3-08CECCA86A33"
        },
        "name": "AnimationScript",
        "enableOnAwake": false,
        "OwnerLink": {
          "@class": "BindingLink",
          "targetId": {
            "uuid": "C145D68B-6803-41E0-B211-6E1BBCE76C35"
          }
        },
        "animation": {
          "uuid": "E958A1EE-5EE8-4545-9FDD-70989DFBF2ED"
        },
        "AnimationType": "object3D",
        "is_imported": true,
        "isEnabled": true
      },
      {
        "@class": "AnimationScript",
        "id": {
          "uuid": "77471901-9845-4562-B568-E573194BE625"
        },
        "name": "AnimationScript",
        "enableOnAwake": false,
        "OwnerLink": {
          "@class": "BindingLink",
          "targetId": {
            "uuid": "C206AD5D-CD50-4D62-820E-48D3510E4644"
          }
        },
        "animation": {
          "uuid": "7F0D74C0-743D-4DAD-B5A9-F8FF3DC96A36"
        },
        "AnimationType": "object3D",
        "is_imported": true,
        "isEnabled": true
      },
      {
        "@class": "AnimationScript",
        "id": {
          "uuid": "DE1418EB-6FC8-4B14-81A8-9CA87B4A8A92"
        },
        "name": "AnimationScript",
        "enableOnAwake": false,
        "OwnerLink": {
          "@class": "BindingLink",
          "targetId": {
            "uuid": "C30E99DA-98D1-4015-A003-0E4319D9439B"
          }
        },
        "animation": {
          "uuid": "31B7A472-EE25-418C-8F5B-993235D550E5"
        },
        "AnimationType": "object3D",
        "is_imported": true,
        "isEnabled": true
      },
      {
        "@class": "AnimationScript",
        "id": {
          "uuid": "96B25033-A154-4AEA-8867-E99DEC4379ED"
        },
        "name": "AnimationScript",
        "enableOnAwake": false,
        "OwnerLink": {
          "@class": "BindingLink",
          "targetId": {
            "uuid": "C310050A-0927-46C3-8873-B5CD0926CA3A"
          }
        },
        "animation": {
          "uuid": "51AAFC5F-60C1-4410-908F-7B906A9B89D4"
        },
        "AnimationType": "object3D",
        "is_imported": true,
        "isEnabled": true
      },
      {
        "@class": "AnimationScript",
        "id": {
          "uuid": "9914D5B0-938C-460E-9A01-3E7427101A7D"
        },
        "name": "AnimationScript",
        "enableOnAwake": false,
        "OwnerLink": {
          "@class": "BindingLink",
          "targetId": {
            "uuid": "C66BFB7A-2489-448D-A3EA-78E1D42EFC68"
          }
        },
        "animation": {
          "uuid": "E979E502-648E-40EE-A769-0FD2532D79B8"
        },
        "AnimationType": "object3D",
        "is_imported": true,
        "isEnabled": true
      },
      {
        "@class": "AnimationScript",
        "id": {
          "uuid": "9E14E042-BEC8-439B-BF28-B7825AA21A44"
        },
        "name": "AnimationScript",
        "enableOnAwake": false,
        "OwnerLink": {
          "@class": "BindingLink",
          "targetId": {
            "uuid": "CFCE513B-15F2-4DFB-9E61-FF531CCCA7AF"
          }
        },
        "animation": {
          "uuid": "2D893041-A6AC-4675-B3BE-8200CFA75CE8"
        },
        "AnimationType": "object3D",
        "is_imported": true,
        "isEnabled": true
      },
      {
        "@class": "AnimationScript",
        "id": {
          "uuid": "AD892EB8-9912-4055-8C9C-E90AD62FD889"
        },
        "name": "AnimationScript",
        "enableOnAwake": false,
        "OwnerLink": {
          "@class": "BindingLink",
          "targetId": {
            "uuid": "D3D9DDDB-A3A4-49AD-A3AC-8903CCDE06D7"
          }
        },
        "animation": {
          "uuid": "56FE12AB-C0B5-4BF9-8DA0-06EBD28F5308"
        },
        "AnimationType": "object3D",
        "is_imported": true,
        "isEnabled": true
      },
      {
        "@class": "AnimationScript",
        "id": {
          "uuid": "2119FD02-F476-471D-89D2-3AF4C11DC57C"
        },
        "name": "AnimationScript",
        "enableOnAwake": false,
        "OwnerLink": {
          "@class": "BindingLink",
          "targetId": {
            "uuid": "DA300B55-C47B-41AC-B09D-D7EF73CBAC93"
          }
        },
        "animation": {
          "uuid": "9F640848-B949-4D7E-9A45-14B1AAA5DCB8"
        },
        "AnimationType": "object3D",
        "is_imported": true,
        "isEnabled": true
      },
      {
        "@class": "AnimationScript",
        "id": {
          "uuid": "002DB0AF-5603-4DCE-9337-9E345BAC00B0"
        },
        "name": "AnimationScript",
        "enableOnAwake": false,
        "OwnerLink": {
          "@class": "BindingLink",
          "targetId": {
            "uuid": "DD7AD1FB-97E9-47FA-83B8-A01010A0C508"
          }
        },
        "animation": {
          "uuid": "4972F035-7DCB-41AE-BE33-63B0F342225B"
        },
        "AnimationType": "object3D",
        "is_imported": true,
        "isEnabled": true
      },
      {
        "@class": "AnimationScript",
        "id": {
          "uuid": "7346F698-8886-4331-841E-A41E7161226C"
        },
        "name": "AnimationScript",
        "enableOnAwake": false,
        "OwnerLink": {
          "@class": "BindingLink",
          "targetId": {
            "uuid": "E644918B-FAD8-4B49-95F8-061799C2AA59"
          }
        },
        "animation": {
          "uuid": "B6F29394-814B-47E4-B031-08D5E19B9980"
        },
        "AnimationType": "object3D",
        "is_imported": true,
        "isEnabled": true
      },
      {
        "@class": "AnimationScript",
        "id": {
          "uuid": "475C2574-78D5-40C0-A960-C79E4F333F68"
        },
        "name": "AnimationScript",
        "enableOnAwake": false,
        "OwnerLink": {
          "@class": "BindingLink",
          "targetId": {
            "uuid": "F7C1F58C-FF50-42B2-A070-C13F3A4547DE"
          }
        },
        "animation": {
          "uuid": "5A4FB97A-2F00-49A3-AE00-E33FF7D121C6"
        },
        "AnimationType": "object3D",
        "is_imported": true,
        "isEnabled": true
      },
      {
        "@class": "AnimationScript",
        "id": {
          "uuid": "98AEA764-368B-4633-95AF-94233638B3A5"
        },
        "name": "AnimationScript",
        "enableOnAwake": false,
        "OwnerLink": {
          "@class": "BindingLink",
          "targetId": {
            "uuid": "F7EF71D9-C8CA-4537-80C7-5AD3FAD845D4"
          }
        },
        "animation": {
          "uuid": "2E544D21-236D-42E5-B785-942D4B2D6271"
        },
        "AnimationType": "object3D",
        "is_imported": true,
        "isEnabled": true
      },
      {
        "@class": "AnimationScript",
        "id": {
          "uuid": "58C39EB3-592E-4C29-A744-7FAB1F56B2CA"
        },
        "name": "AnimationScript",
        "enableOnAwake": false,
        "OwnerLink": {
          "@class": "BindingLink",
          "targetId": {
            "uuid": "F9592BCE-F645-4DC2-85F5-4C7866F09D00"
          }
        },
        "animation": {
          "uuid": "DB330AD1-8C3E-4886-AF2A-A5569DCBDC1F"
        },
        "AnimationType": "object3D",
        "is_imported": true,
        "isEnabled": true
      },
      {
        "@class": "AnimationScript",
        "id": {
          "uuid": "DDE397DA-C1EC-40AA-AB87-2986BBC8A4E7"
        },
        "name": "AnimationScript",
        "enableOnAwake": false,
        "OwnerLink": {
          "@class": "BindingLink",
          "targetId": {
            "uuid": "FDCD3CEF-339E-46B6-84B9-5A17E73D209F"
          }
        },
        "animation": {
          "uuid": "B7C68B2B-F437-47A0-A653-B066EB57F3D2"
        },
        "AnimationType": "object3D",
        "is_imported": true,
        "isEnabled": true
      },
      {
        "@class": "AnimationScript",
        "id": {
          "uuid": "5E072511-63F5-4774-908D-5388366E307A"
        },
        "name": "AnimationScript",
        "enableOnAwake": false,
        "OwnerLink": {
          "@class": "BindingLink",
          "targetId": {
            "uuid": "FE26DD51-E009-4AB0-9C3F-BB9024DED86C"
          }
        },
        "animation": {
          "uuid": "CFBC0413-3676-47FE-98DB-A382DA08D507"
        },
        "AnimationType": "object3D",
        "is_imported": true,
        "isEnabled": true
      }
    ]
  },
  "triggers": []
}
